OBP_monitoring_v1/__init__.py
OBP_monitoring_v1/asg_elb_healthcheck_required.py
OBP_monitoring_v1/ec2_instance_detailed_monitoring_enabled.py
OBP_monitoring_v1/guard_duty_enabled.py
OBP_monitoring_v1/lambda_concurrency_check.py
OBP_monitoring_v1/lambda_dlq_check.py
OBP_monitoring_v1/rds_enhanced_monitoring_enabled.py
OBP_monitoring_v1/s3_event_notifications_enabled.py
OBP_monitoring_v1/utils.py
OBP_monitoring_v1-0.0.1.dist-info/METADATA
OBP_monitoring_v1-0.0.1.dist-info/WHEEL
OBP_monitoring_v1-0.0.1.dist-info/top_level.txt
OBP_monitoring_v1-0.0.1.dist-info/RECORD
